django_modern_user/__init__.py
django_modern_user/admin.py
django_modern_user/apps.py
django_modern_user/migrations/0001_initial.py
django_modern_user/migrations/__init__.py
django_modern_user/models.py
django_modern_user/tests.py
django_modern_user/views.py
django_modern_user-5.0.0.dist-info/LICENSE
django_modern_user-5.0.0.dist-info/METADATA
django_modern_user-5.0.0.dist-info/WHEEL
django_modern_user-5.0.0.dist-info/RECORD
