Metadata-Version: 2.3
Name: django-modern-user
Version: 5.0.0
Summary: An improved custom user model for django projects
License: MIT
Author: Christopher Kumm
Author-email: chrislkumm@protonmail.com
Requires-Python: >=3.10,<3.14
Classifier: License :: OSI Approved :: MIT License
Classifier: Programming Language :: Python :: 3
Classifier: Programming Language :: Python :: 3.10
Classifier: Programming Language :: Python :: 3.11
Classifier: Programming Language :: Python :: 3.12
Classifier: Programming Language :: Python :: 3.13
Requires-Dist: django (>=4.2,<6.0)
Project-URL: Repository, https://github.com/ChrisCrossCrash/django-modern-user
